atf/__init__.py
atf/common/Common.py
atf/common/__init__.py
atf/common/docker/__init__.py
atf/common/docker/client.py
atf/common/network/Network.py
atf/common/network/__init__.py
atf/common/pcapreplay/PcapReplay.py
atf/common/pcapreplay/PcapReplayBase.py
atf/common/pcapreplay/PcapReplayInfo.py
atf/common/pcapreplay/PcapReplayTest.py
atf/common/pcapreplay/Protocol.py
atf/common/pcapreplay/TestSuite.py
atf/common/pcapreplay/TimeoutMethod.py
atf/common/pcapreplay/__init__.py
atf/common/pcapreplay/flow/Flow.py
atf/common/pcapreplay/flow/FlowKey.py
atf/common/pcapreplay/flow/FlowTest.py
atf/common/pcapreplay/flow/GenericFlow.py
atf/common/pcapreplay/flow/IcmpFlow.py
atf/common/pcapreplay/flow/IpFlowKey.py
atf/common/pcapreplay/flow/Ipv4FlowKey.py
atf/common/pcapreplay/flow/Ipv6FlowKey.py
atf/common/pcapreplay/flow/MacFlowKey.py
atf/common/pcapreplay/flow/TcpFlow.py
atf/common/pcapreplay/flow/UdpFlow.py
atf/common/pcapreplay/flow/__init__.py
atf/common/pcapreplay/trigger/HttpTrigger.py
atf/common/pcapreplay/trigger/TcpTrigger.py
atf/common/pcapreplay/trigger/Trigger.py
atf/common/pcapreplay/trigger/TriggerTest.py
atf/common/pcapreplay/trigger/__init__.py
atf/common/report/DocStringParser.py
atf/common/report/TestReport.py
atf/common/report/TestReportGenerator.py
atf/common/report/TestResult.py
atf/common/report/__init__.py
atf/common/utils/__init__.py
atf/common/utils/dspawn.py
atf/common/webservice/Auth.py
atf/common/webservice/Request.py
atf/common/webservice/Response.py
atf/common/webservice/Session.py
atf/common/webservice/WebService.py
atf/common/webservice/__init__.py
atf/framework/FrameworkBase.py
atf/framework/ISSTestBase.py
atf/framework/RunConfig.py
atf/framework/SystemConfig.py
atf/framework/__init__.py
atf/framework/device/DeviceConfig.py
atf/framework/device/DeviceNetwork.py
atf/framework/device/PDocker.py
atf/framework/device/ProxyContainer.py
atf/framework/device/ProxyDevice.py
atf/framework/device/ProxyDocker.py
atf/framework/device/ProxyEmulator.py
atf_docker-0.0.1.dist-info/LICENSE
atf_docker-0.0.1.dist-info/METADATA
atf_docker-0.0.1.dist-info/WHEEL
atf_docker-0.0.1.dist-info/top_level.txt
atf_docker-0.0.1.dist-info/RECORD
