Metadata-Version: 2.1
Name: atf-docker
Version: 0.0.1
Summary: ATF for docker
Home-page: https://github.com/jkclee/atf
Author: johnklee
Author-email: kueiching.a.lee@rakuten.com
License: UNKNOWN
Platform: UNKNOWN
Requires-Python: ~=3.6
Requires-Dist: certifi (==2019.9.11)
Requires-Dist: chardet (==3.0.4)
Requires-Dist: docker (==4.1.0)
Requires-Dist: idna (==2.8)
Requires-Dist: pexpect (==4.7.0)
Requires-Dist: ptyprocess (==0.6.0)
Requires-Dist: requests (==2.22.0)
Requires-Dist: six (==1.12.0)
Requires-Dist: urllib3 (==1.24.3)
Requires-Dist: websocket-client (==0.56.0)
Requires-Dist: coloredlogs (==10.0)
